{
  "project_info": {
    "project_number": "556517599680",
    "project_id": "filtar-fc039",
    "storage_bucket": "filtar-fc039.appspot.com"
  },
  "client": [
    {
      "client_info": {
        "mobilesdk_app_id": "1:556517599680:android:99425dfb3b559076498025",
        "android_client_info": {
          "package_name": "com.app.filtar"
        }
      },
      "oauth_client": [
        {
          "client_id": "556517599680-0jcahc9echcj7e82ro07na6lssppp0ac.apps.googleusercontent.com",
          "client_type": 1,
          "android_info": {
            "package_name": "com.app.filtar",
            "certificate_hash": "96e7fa9697746fde1f96c6f423f3f70e8490dc5f"
          }
        },
        {
          "client_id": "556517599680-15grd5bbspsemh85939sn70h0372838s.apps.googleusercontent.com",
          "client_type": 1,
          "android_info": {
            "package_name": "com.app.filtar",
            "certificate_hash": "019e7fba751f4222135b4b0a6cfe78d742885eea"
          }
        },
        {
          "client_id": "556517599680-vs5520pf67fdh85uim15afmtacpnkona.apps.googleusercontent.com",
          "client_type": 1,
          "android_info": {
            "package_name": "com.app.filtar",
            "certificate_hash": "636ec7f8e9ebc097d9417189972ef8f1feb676f4"
          }
        },
        {
          "client_id": "556517599680-kiphud2ct8upoom8qsqfrg4t4pd4n821.apps.googleusercontent.com",
          "client_type": 3
        }
      ],
      "api_key": [
        {
          "current_key": "AIzaSyAg5WSBHGfiZsyzRklS5FBIyuzZGkyVmGw"
        }
      ],
      "services": {
        "appinvite_service": {
          "other_platform_oauth_client": [
            {
              "client_id": "556517599680-kiphud2ct8upoom8qsqfrg4t4pd4n821.apps.googleusercontent.com",
              "client_type": 3
            }
          ]
        }
      }
    },
    {
      "client_info": {
        "mobilesdk_app_id": "1:556517599680:android:dc9773635433d3a2498025",
        "android_client_info": {
          "package_name": "com.elmoselhy.elfiltardelivery"
        }
      },
      "oauth_client": [
        {
          "client_id": "556517599680-seue00c3fqaif8gnre26j0lfj6supv9f.apps.googleusercontent.com",
          "client_type": 1,
          "android_info": {
            "package_name": "com.elmoselhy.elfiltardelivery",
            "certificate_hash": "0dbd042fb625d69903bf8aea8dd1a87c940281a2"
          }
        },
        {
          "client_id": "556517599680-kiphud2ct8upoom8qsqfrg4t4pd4n821.apps.googleusercontent.com",
          "client_type": 3
        }
      ],
      "api_key": [
        {
          "current_key": "AIzaSyAg5WSBHGfiZsyzRklS5FBIyuzZGkyVmGw"
        }
      ],
      "services": {
        "appinvite_service": {
          "other_platform_oauth_client": [
            {
              "client_id": "556517599680-kiphud2ct8upoom8qsqfrg4t4pd4n821.apps.googleusercontent.com",
              "client_type": 3
            }
          ]
        }
      }
    }
  ],
  "configuration_version": "1"
}